aws_cost_optimization_1/__init__.py
aws_cost_optimization_1/utils.py
aws_cost_optimization_1-0.1.1.dist-info/LICENCE
aws_cost_optimization_1-0.1.1.dist-info/METADATA
aws_cost_optimization_1-0.1.1.dist-info/WHEEL
aws_cost_optimization_1-0.1.1.dist-info/top_level.txt
aws_cost_optimization_1-0.1.1.dist-info/RECORD
